onefeed/__init__.py
onefeed/__version__.py
onefeed/cmdline.py
onefeed/config.py
onefeed/app/__init__.py
onefeed/app/db.py
onefeed/app/sql.py
onefeed/app/blueprints/__init__.py
onefeed/app/blueprints/api.py
onefeed/app/blueprints/homepage.py
onefeed/app/static/CNAME
onefeed/app/static/asset-manifest.json
onefeed/app/static/favicon.png
onefeed/app/static/home_bg.png
onefeed/app/static/layouts__BasicLayout.bb69fe50.async.js
onefeed/app/static/p__Favorites.07380d1d.async.js
onefeed/app/static/p__Favorites.c9ded593.chunk.css
onefeed/app/static/p__Favorites~p__Github~p__Hackernews~p__Infoq.22111fd3.chunk.css
onefeed/app/static/p__Favorites~p__Github~p__Hackernews~p__Infoq.37331b80.async.js
onefeed/app/static/p__Github.2d7cfe96.chunk.css
onefeed/app/static/p__Github.fa318412.async.js
onefeed/app/static/p__Hackernews.098af1a0.chunk.css
onefeed/app/static/p__Hackernews.3b766cbc.async.js
onefeed/app/static/p__Infoq.0569f793.async.js
onefeed/app/static/p__Infoq.6d38c1b6.chunk.css
onefeed/app/static/pro_icon.svg
onefeed/app/static/umi.5222c8a2.css
onefeed/app/static/umi.f12caaaf.js
onefeed/app/static/icons/icon-128x128.png
onefeed/app/static/icons/icon-192x192.png
onefeed/app/static/icons/icon-512x512.png
onefeed/app/static/static/logo.f0355d39.svg
onefeed/app/templates/index.html
onefeed/retriever/__init__.py
onefeed/retriever/db.py
onefeed/retriever/retriever.py
onefeed/retriever/sql.py
onefeed/retriever/utils.py
onefeed/retriever/github/__init__.py
onefeed/retriever/github/items.py
onefeed/retriever/github/pipelines.py
onefeed/retriever/github/settings.py
onefeed/retriever/github/spiders/__init__.py
onefeed/retriever/github/spiders/trending.py
onefeed/retriever/hackernews/__init__.py
onefeed/retriever/hackernews/items.py
onefeed/retriever/hackernews/pipelines.py
onefeed/retriever/hackernews/settings.py
onefeed/retriever/hackernews/spiders/__init__.py
onefeed/retriever/hackernews/spiders/homepage.py
onefeed/retriever/infoq/__init__.py
onefeed/retriever/infoq/items.py
onefeed-0.4.0.dist-info/LICENSE
onefeed-0.4.0.dist-info/METADATA
onefeed-0.4.0.dist-info/WHEEL
onefeed-0.4.0.dist-info/entry_points.txt
onefeed-0.4.0.dist-info/top_level.txt
onefeed-0.4.0.dist-info/RECORD
