Metadata-Version: 2.1
Name: onefeed
Version: 0.4.0
Summary: Info feed only for yourself
Home-page: https://github.com/dadaers/OneFeed
Author: anorakj
Author-email: nicholasjcc@gmail.com
License: Apache 2.0
Platform: UNKNOWN
Classifier: Programming Language :: Python :: 3.6
Classifier: Programming Language :: Python :: 3.7
Classifier: License :: OSI Approved :: Apache Software License
Classifier: Operating System :: OS Independent
Requires-Python: >=3.6
Requires-Dist: Scrapy (>=2.3.0)
Requires-Dist: Flask (>=1.1.2)
Requires-Dist: pyasn1
Requires-Dist: crochet
